CHANGELOG.rst
LICENSE.txt
MANIFEST.in
README.rst
TODO.rst
VERSION.txt
setup.cfg
setup.py
test-requirements.txt
doc/manual.rst
jstc/__init__.py
jstc/api.py
jstc/compiler.py
jstc/test_compiler.py
jstc.egg-info/PKG-INFO
jstc.egg-info/SOURCES.txt
jstc.egg-info/dependency_links.txt
jstc.egg-info/entry_points.txt
jstc.egg-info/requires.txt
jstc.egg-info/top_level.txt
jstc.egg-info/zip-safe
jstc/engines/__init__.py
jstc/engines/base.py
jstc/engines/handlebars.py
jstc/engines/mustache.py
jstc/engines/test_handlebars.py
jstc/engines/test_mustache.py