Metadata-Version: 1.1
Name: jstc
Version: 0.1.7
Summary: Server-side JavaScript template compilation and packaging
Home-page: http://github.com/canaryhealth/jstc
Author: Philip J Grabner, Canary Health Inc
Author-email: oss@canary.md
License: MIT (http://opensource.org/licenses/MIT)
Keywords: javascript server-side template compiler packager
Platform: UNKNOWN
Classifier: Intended Audience :: Developers
Classifier: Programming Language :: Python
Classifier: Operating System :: OS Independent
Classifier: Topic :: Internet
Classifier: Topic :: Software Development
Classifier: Topic :: Internet :: WWW/HTTP
Classifier: Natural Language :: English
Classifier: License :: OSI Approved :: MIT License
Classifier: License :: Public Domain
